{"otherData": {},"traceEvents":[{"cat":"function","dur":101283,"name":"glfwInit","ph":"X","pid":0,"tid":3696737158,"ts":1825163023149},{"cat":"function","dur":650923,"name":"glfwCreateWindow","ph":"X","pid":0,"tid":3696737158,"ts":1825163124721},{"cat":"function","dur":10140,"name":"void __cdecl Engine::OpenGLContext::Init(void)","ph":"X","pid":0,"tid":3696737158,"ts":1825163775778},{"cat":"function","dur":37,"name":"void __cdecl Engine::WindowsWindow::SetVSync(bool)","ph":"X","pid":0,"tid":3696737158,"ts":1825163786009},{"cat":"function","dur":764285,"name":"void __cdecl Engine::WindowsWindow::Init(const struct Engine::WindowProps &)","ph":"X","pid":0,"tid":3696737158,"ts":1825163021829},{"cat":"function","dur":764335,"name":"__cdecl Engine::WindowsWindow::WindowsWindow(const struct Engine::WindowProps &)","ph":"X","pid":0,"tid":3696737158,"ts":1825163021829},{"cat":"function","dur":23,"name":"void __cdecl Engine::WindowsWindow::SetVSync(bool)","ph":"X","pid":0,"tid":3696737158,"ts":1825163786244},{"cat":"function","dur":7,"name":"void __cdecl Engine::OpenGLRendererAPI::Init(void)","ph":"X","pid":0,"tid":3696737158,"ts":1825163786325},{"cat":"function","dur":23,"name":"__cdecl Engine::OpenGLVertexArray::OpenGLVertexArray(void)","ph":"X","pid":0,"tid":3696737158,"ts":1825163786424},{"cat":"function","dur":18,"name":"__cdecl Engine::OpenGLVertexBuffer::OpenGLVertexBuffer(void *,unsigned int)","ph":"X","pid":0,"tid":3696737158,"ts":1825163786553},{"cat":"function","dur":2,"name":"void __cdecl Engine::OpenGLVertexBuffer::Bind(void) const","ph":"X","pid":0,"tid":3696737158,"ts":1825163786835},{"cat":"function","dur":233,"name":"void __cdecl Engine::OpenGLVertexArray::AddVertexBuffer(const class std::shared_ptr<class Engine::VertexBuffer> &)","ph":"X","pid":0,"tid":3696737158,"ts":1825163786663},{"cat":"function","dur":52,"name":"__cdecl Engine::OpenGLIndexBuffer::OpenGLIndexBuffer(void *,unsigned int)","ph":"X","pid":0,"tid":3696737158,"ts":1825163786946},{"cat":"function","dur":0,"name":"void __cdecl Engine::OpenGLIndexBuffer::Bind(void) const","ph":"X","pid":0,"tid":3696737158,"ts":1825163787066},{"cat":"function","dur":56,"name":"void __cdecl Engine::OpenGLVertexArray::SetIndexBuffer(const class std::shared_ptr<class Engine::IndexBuffer> &)","ph":"X","pid":0,"tid":3696737158,"ts":1825163787059},{"cat":"function","dur":22,"name":"__cdecl Engine::OpenGLTexture2D::OpenGLTexture2D(unsigned int,unsigned int)","ph":"X","pid":0,"tid":3696737158,"ts":1825163787179},{"cat":"function","dur":11,"name":"void __cdecl Engine::OpenGLTexture2D::SetData(void *,unsigned int)","ph":"X","pid":0,"tid":3696737158,"ts":1825163787259},{"cat":"function","dur":238,"name":"class std::basic_string<char,struct std::char_traits<char>,class std::allocator<char> > __cdecl Engine::OpenGLShader::ReadFile(const class std::basic_string<char,struct std::char_traits<char>,class std::allocator<char> > &)","ph":"X","pid":0,"tid":3696737158,"ts":1825163787341},{"cat":"function","dur":126,"name":"class std::unordered_map<unsigned int,class std::basic_string<char,struct std::char_traits<char>,class std::allocator<char> >,struct std::hash<unsigned int>,struct std::equal_to<unsigned int>,class std::allocator<struct std::pair<unsigned int const ,class std::basic_string<char,struct std::char_traits<char>,class std::allocator<char> > > > > __cdecl Engine::OpenGLShader::PreProcess(const class std::basic_string<char,struct std::char_traits<char>,class std::allocator<char> > &)","ph":"X","pid":0,"tid":3696737158,"ts":1825163787644},{"cat":"function","dur":3543,"name":"void __cdecl Engine::OpenGLShader::Compile(const class std::unordered_map<unsigned int,class std::basic_string<char,struct std::char_traits<char>,class std::allocator<char> >,struct std::hash<unsigned int>,struct std::equal_to<unsigned int>,class std::allocator<struct std::pair<unsigned int const ,class std::basic_string<char,struct std::char_traits<char>,class std::allocator<char> > > > > &)","ph":"X","pid":0,"tid":3696737158,"ts":1825163787827},{"cat":"function","dur":4152,"name":"__cdecl Engine::OpenGLShader::OpenGLShader(const class std::basic_string<char,struct std::char_traits<char>,class std::allocator<char> > &)","ph":"X","pid":0,"tid":3696737158,"ts":1825163787337},{"cat":"function","dur":3,"name":"void __cdecl Engine::OpenGLShader::Bind(void) const","ph":"X","pid":0,"tid":3696737158,"ts":1825163791612},{"cat":"function","dur":44,"name":"void __cdecl Engine::OpenGLShader::SetInt(const class std::basic_string<char,struct std::char_traits<char>,class std::allocator<char> > &,int)","ph":"X","pid":0,"tid":3696737158,"ts":1825163791671},{"cat":"function","dur":0,"name":"void __cdecl Engine::OpenGLShader::Unbind(void) const","ph":"X","pid":0,"tid":3696737158,"ts":1825163791776},{"cat":"function","dur":5435,"name":"void __cdecl Engine::Renderer2D::Init(void)","ph":"X","pid":0,"tid":3696737158,"ts":1825163786388},{"cat":"function","dur":5546,"name":"void __cdecl Engine::Renderer::Init(void)","ph":"X","pid":0,"tid":3696737158,"ts":1825163786324},{"cat":"function","dur":1450,"name":"void __cdecl Engine::ImGuiLayer::OnAttach(void)","ph":"X","pid":0,"tid":3696737158,"ts":1825163791945},{"cat":"function","dur":1550,"name":"void __cdecl Engine::Application::PushOverlay(class Engine::Layer *)","ph":"X","pid":0,"tid":3696737158,"ts":1825163791937},{"cat":"function","dur":771742,"name":"__cdecl Engine::Application::Application(const struct Engine::ApplicationProps &)","ph":"X","pid":0,"tid":3696737158,"ts":1825163021800},{"cat":"function","dur":5,"name":"__cdecl Engine::OrthographicCamera::OrthographicCamera(float,float,float,float)","ph":"X","pid":0,"tid":3696737158,"ts":1825163793609},{"cat":"function","dur":254,"name":"stbi_load - OpenGLTexture2D::OpenGLTexture2D(const std::string&) stbi_load","ph":"X","pid":0,"tid":3696737158,"ts":1825163793676},{"cat":"function","dur":357,"name":"__cdecl Engine::OpenGLTexture2D::OpenGLTexture2D(const class std::basic_string<char,struct std::char_traits<char>,class std::allocator<char> > &)","ph":"X","pid":0,"tid":3696737158,"ts":1825163793676},{"cat":"function","dur":414,"name":"void __cdecl Sandbox2D::OnAttach(void)","ph":"X","pid":0,"tid":3696737158,"ts":1825163793671},{"cat":"function","dur":469,"name":"void __cdecl Engine::Application::PushLayer(class Engine::Layer *)","ph":"X","pid":0,"tid":3696737158,"ts":1825163793663}]}